{"TitleInfo":{"Genre":["sf_heroic"],"GenreType":null,"Author":[{"FirstName":"Алексей","MiddleName":"Алексеевич","LastName":"Ковальчук","Nickname":"","HomePage":"","Email":""}],"BookTitle":"Право на выбор","Annotation":{"P":["Ветер перемен редко возникает внезапно, а его первые порывы обычно становятся заметны для многих людей. Но иногда так бывает, что лёгкий и не предвещающий беды ветерок стремительно превращается в настоящий ураган, сметающий с лица земли государства и превращая в пепел целые империи.","И Сергею придётся очень скоро осознать одну простую истину: не стоит расслабляться, даже если тебя окружают роскошные и шикарные женщины, следует всегда помнить, что любая красота может стать смертельно опасной. В запасе всего лишь несколько часов, на кону жизнь близких тебе людей и не так много возможностей повлиять на ситуацию. Куда бежать и что делать? Как сражаться против заведомо более сильного врага? А ещё нужно спасти наследную принцессу престола Российской империи, вырваться из окружения и сделать, наверное, самый главный выбор своей жизни."]},"Keywords":"параллельные миры,магические способности,становление героя,любовные приключения","Date":"2021-05-13","Coverpage":{"Image":{"Href":"#PnV.jpg"}},"Lang":"ru","SrcLang":"","Translator":{"FirstName":"","MiddleName":"","LastName":"","Nickname":"","HomePage":"","Email":""},"Sequence":""},"DocumentInfo":{"Author":[{"FirstName":"Руслан","MiddleName":"","LastName":"Волченко","Nickname":"Ruslan","HomePage":"","Email":""},{"FirstName":"","MiddleName":"","LastName":"","Nickname":"Colourban","HomePage":"","Email":""}],"ProgramUsed":"OOoFBTools-3.0 (ExportToFB21), FictionBook Editor Release 2.6.6","Date":"13 May 2021","SrcURL":["http://www.litres.ru/pages/biblio_book/?art=65086482"],"SrcOcr":"Текст предоставлен правообладателем","ID":"0d40041e-b303-11eb-9deb-441ea152441c","Version":1.01,"History":{"P":["v 1.0 — Создание fb2 из издательского текста (Ruslan)","1.01 — уменьшена обложка"]}},"PublishInfo":{"BookName":"","Publisher":"","City":"","Year":0,"ISBN":"","Sequence":""},"CustomInfo":[{"InfoType":""}]}