{"TitleInfo":{"Genre":["sf_fantasy","sf_action","popadanec"],"GenreType":null,"Author":[{"FirstName":"Денис","MiddleName":"Игоревич","LastName":"Щелкунов","Nickname":"","HomePage":"","Email":""}],"BookTitle":"Далекий шанс","Annotation":{"P":["Позвольте представиться, Дубнов Максим Николаевич. Родился в 487 году космической эры, и через два месяца буду праздновать своё 32-летие. Экскурсия на Землю, в которой я сейчас участвую, приурочена к окончанию мной университета, по специальности конструктора саморазвивающихся информационных систем. Сейчас я со своей группой лечу отмечать это знаменательное событие. Долгие десять лет учёбы наконец-то пройдены и меня, несомненно, ждёт только счастливое будущее!","Если, конечно, выживу в новом мире. Мире… магии."]},"Keywords":"","Date":"2016","Coverpage":{"Image":{"Href":"#cover.jpg"}},"Lang":"ru","SrcLang":"","Translator":{"FirstName":"","MiddleName":"","LastName":"","Nickname":"","HomePage":"","Email":""},"Sequence":""},"DocumentInfo":{"Author":[{"FirstName":"","MiddleName":"","LastName":"","Nickname":"","HomePage":"","Email":""}],"ProgramUsed":"FictionBook Editor Release 2.6.7","Date":"06.09.2016","SrcURL":null,"SrcOcr":"авторский текст","ID":"452ABE61-6AE3-421E-B130-717FEBD8A6EF","Version":1,"History":{"P":["1.0"]}},"PublishInfo":{"BookName":"","Publisher":"","City":"","Year":0,"ISBN":"","Sequence":""},"CustomInfo":null}